{
  "blurb": "Intervals represent periods of time measured in months, days, microseconds, or a combination thereof.",
  "layout": "docu",
  "redirect_from": [
    "/docs/sql/data_types/interval"
  ],
  "title": "Interval Type",
  "file_name": "interval.md",
  "file_stem": "interval",
  "file_path": "sql/data_types/interval.md",
  "file_size": 8051,
  "document_id": "sql-data_types-interval",
  "url": "/sql/data_types/interval",
  "content_hash": "dbbc8c6de4b4de7825b1b0bd26a64f05",
  "statistics": {
    "char_count": 7278,
    "word_count": 1112,
    "line_count": 147,
    "paragraph_count": 35,
    "header_count": 3,
    "code_block_count": 8,
    "code_lines": 47
  },
  "processed_at": "2025-11-22T10:32:12.424832",
  "sections": [
    {
      "level": 2,
      "title": "Arithmetic with Timestamps, Dates and Intervals",
      "anchor": "arithmetic-with-timestamps-dates-and-intervals"
    },
    {
      "level": 2,
      "title": "Equality and Comparison",
      "anchor": "equality-and-comparison"
    },
    {
      "level": 2,
      "title": "Functions",
      "anchor": "functions"
    }
  ]
}